ImageProcessorsModule/KerasGeneratorProcessors.py
ImageProcessorsModule/MakeTFRecordProcessors.py
ImageProcessorsModule/TFDataSetProcessors.py
ImageProcessorsModule/TFRecordWriter.py
ImageProcessorsModule/__init__.py
PyTorchDataSets/ConstantProcessors.py
PyTorchDataSets/RelativeProcessors.py
PyTorchDataSets/__init__.py
TFDataSets/ConstantProcessors.py
TFDataSets/RelativeProcessors.py
TFDataSets/SpecialProcessors.py
TFDataSets/TFGenerator.py
TFDataSets/__init__.py
ImageProcessorsModule-1.0.4.dist-info/METADATA
ImageProcessorsModule-1.0.4.dist-info/WHEEL
ImageProcessorsModule-1.0.4.dist-info/top_level.txt
ImageProcessorsModule-1.0.4.dist-info/RECORD
