Metadata-Version: 2.2
Name: ImageProcessorsModule
Version: 1.0.4
Summary: Services for processing and creating TensorFlow or PyTorch records
Author-email: Brian Mark Anderson <markba122@gmail.com>
License: GNU Affero General Public License v3
Project-URL: Homepage, https://github.com/brianmanderson/Image_Processors_Module
Project-URL: Repository, https://github.com/brianmanderson/Image_Processors_Module
Classifier: Programming Language :: Python :: 3
Classifier: License :: OSI Approved :: GNU Affero General Public License v3
Requires-Python: >=3.8
